devdeps/__init__.py
devdeps/_version.py
dev_dependencies-0.1.1.dist-info/LICENSE
dev_dependencies-0.1.1.dist-info/METADATA
dev_dependencies-0.1.1.dist-info/WHEEL
dev_dependencies-0.1.1.dist-info/top_level.txt
dev_dependencies-0.1.1.dist-info/RECORD
