Metadata-Version: 2.1
Name: dev-dependencies
Version: 0.1.1
Summary: An opinionated library of dev-time dependencies
Author: Justin Mills
License: MIT
Keywords: library,dependencies
Requires-Python: >=3.11
License-File: LICENSE
Requires-Dist: pydantic
Requires-Dist: black
Requires-Dist: flake8
Requires-Dist: flake8-black
Requires-Dist: ruff
Requires-Dist: mypy
Requires-Dist: pytest
Requires-Dist: pytest-cov
Requires-Dist: pytest-xdist
Requires-Dist: pytest-mock
Requires-Dist: pytest-md
Requires-Dist: pytest-emoji
